hedgepig_logger/__init__.py
hedgepig_logger/logger.py
hedgepig_logger/writeConfig.py
hedgepig_logger-0.2.0.dist-info/LICENSE
hedgepig_logger-0.2.0.dist-info/METADATA
hedgepig_logger-0.2.0.dist-info/WHEEL
hedgepig_logger-0.2.0.dist-info/top_level.txt
hedgepig_logger-0.2.0.dist-info/RECORD
