Metadata-Version: 2.1
Name: hedgepig-logger
Version: 0.2.0
Summary: Lightweight logging in Python without timestamps or info labels.
Home-page: http://github.com/drgriffis/hedgepig-logger
Author: Denis Newman-Griffis
Author-email: denis.newman.griffis@gmail.com
License: UNKNOWN
Platform: UNKNOWN
Classifier: Programming Language :: Python :: 3
Classifier: License :: OSI Approved :: MIT License
Classifier: Operating System :: OS Independent
License-File: LICENSE
